sei_client/__init__.py
sei_client/seiclient.py
sei_client-0.1.4.dist-info/WHEEL
sei_client-0.1.4.dist-info/METADATA
sei_client-0.1.4.dist-info/RECORD
