Metadata-Version: 2.1
Name: sei-client
Version: 0.1.4
Summary: 
Author: Julio Cezar Riffel
Author-email: julioriffel@gmail.com
Requires-Python: >=3.8,<4.0
Classifier: Programming Language :: Python :: 3
Classifier: Programming Language :: Python :: 3.10
Classifier: Programming Language :: Python :: 3.8
Classifier: Programming Language :: Python :: 3.9
Requires-Dist: requests (>=2.26.0,<3.0.0)
